imuthes/alchemy/intpk/__init__.py
imuthes/alchemy/intpk/add_column.py
imuthes/alchemy/intpk/base.py
imuthes/alchemy/intpk/bidirectional_relationship.py
imuthes/alchemy/intpk/change_column.py
imuthes/alchemy/intpk/cli/__init__.py
imuthes/alchemy/intpk/cli/crud.py
imuthes/alchemy/intpk/cli/crud_activate.py
imuthes/alchemy/intpk/cli/crud_add.py
imuthes/alchemy/intpk/cli/crud_change.py
imuthes/alchemy/intpk/cli/crud_deactivate.py
imuthes/alchemy/intpk/cli/crud_factory.py
imuthes/alchemy/intpk/cli/crud_list.py
imuthes/alchemy/intpk/cli/get_dynamic_param_decls.py
imuthes/alchemy/intpk/cli/main.py
imuthes/alchemy/intpk/exceptions/__init__.py
imuthes/alchemy/intpk/exceptions/status_change_not_permitted_error.py
imuthes/alchemy/intpk/filter_column.py
imuthes/alchemy/intpk/searchable.py
imuthes/alchemy/intpk/status.py
imuthes/alchemy/intpk/to_snake_case.py
imuthes/alchemy/intpk/versioned.py
imuthes_alchemy_intpk-0.0.0a0.dist-info/METADATA
imuthes_alchemy_intpk-0.0.0a0.dist-info/WHEEL
imuthes_alchemy_intpk-0.0.0a0.dist-info/RECORD
